LICENSE
MANIFEST.in
README
requirements.txt
setup.py
test_settings.py
datatables/__init__.py
datatables/columns.py
datatables/datatable.py
datatables/decorators.py
datatables/models.py
datatables/utils.py
datatables/static/datatables/3-state-checkbox.gif
datatables/static/datatables/checkbox_column.css
datatables/static/datatables/checkbox_column.js
datatables/static/datatables/checkbox_column_new.js
datatables/templates/datatables/checkbox_column.html
datatables/templates/datatables/checkbox_column_label.html
datatables/templates/datatables/table.html
datatables/templatetags/__init__.py
datatables/templatetags/lookupattr.py
django_datatables.egg-info/PKG-INFO
django_datatables.egg-info/SOURCES.txt
django_datatables.egg-info/dependency_links.txt
django_datatables.egg-info/not-zip-safe
django_datatables.egg-info/requires.txt
django_datatables.egg-info/top_level.txt
docs/Makefile
docs/conf.py
docs/index.rst
docs/make.bat
test_app/__init__.py
test_app/models.py
test_app/tests.py
test_app/urls.py
test_app/views.py
test_app/static/css/demo_table.css
test_app/static/css/demo_table_jui.css
test_app/static/css/start/jquery-ui-1.8.16.custom.css
test_app/static/css/start/images/ui-bg_flat_55_999999_40x100.png
test_app/static/css/start/images/ui-bg_flat_75_aaaaaa_40x100.png
test_app/static/css/start/images/ui-bg_glass_45_0078ae_1x400.png
test_app/static/css/start/images/ui-bg_glass_55_f8da4e_1x400.png
test_app/static/css/start/images/ui-bg_glass_75_79c9ec_1x400.png
test_app/static/css/start/images/ui-bg_gloss-wave_45_e14f1c_500x100.png
test_app/static/css/start/images/ui-bg_gloss-wave_50_6eac2c_500x100.png
test_app/static/css/start/images/ui-bg_gloss-wave_75_2191c0_500x100.png
test_app/static/css/start/images/ui-bg_inset-hard_100_fcfdfd_1x100.png
test_app/static/css/start/images/ui-icons_0078ae_256x240.png
test_app/static/css/start/images/ui-icons_056b93_256x240.png
test_app/static/css/start/images/ui-icons_d8e7f3_256x240.png
test_app/static/css/start/images/ui-icons_e0fdff_256x240.png
test_app/static/css/start/images/ui-icons_f5e175_256x240.png
test_app/static/css/start/images/ui-icons_f7a50d_256x240.png
test_app/static/css/start/images/ui-icons_fcd113_256x240.png
test_app/static/images/back_disabled.jpg
