Metadata-Version: 1.0
Name: django-datatables
Version: 0.1.0-r34
Summary: Django integration of DataTables jQuery plugin.
Home-page: https://projects.ninemoreminutes.com/projects/django-datatables/
Author: Nine More Minutes, Inc.
Author-email: support@ninemoreminutes.com
License: BSD
Keywords: django datatables jquery tables
Platform: UNKNOWN
Classifier: Development Status :: 1 - Planning
Classifier: Environment :: Web Environment
Classifier: Framework :: Django
Classifier: Intended Audience :: Developers
Classifier: License :: OSI Approved :: BSD License
Classifier: Operating System :: OS Independent
Classifier: Programming Language :: Python
Classifier: Topic :: Internet :: WWW/HTTP
Classifier: Topic :: Software Development :: Libraries
